{
    "Постомат bananies": {
        "price": 1500.0,
        "income": "200",
        "consumption": "93"
    },
    "Пункт выдачи bananies": {
        "price": 35000.0,
        "income": "550",
        "consumption": "150"
    },
    "Склад bananies": {
        "price": 75000.0,
        "income": "1350",
        "consumption": "270"
    },
    "Магазин красный ботинок": {
        "price": 100000.0,
        "income": "730",
        "consumption": "130"
    },
    "Кафе кофеёк": {
        "price": 625000.0,
        "income": "1000",
        "consumption": "230"
    },
    "Гипермаркет полоска": {
        "price": 1750000.0,
        "income": "2300",
        "consumption": "510"
    },
    "Пенькофф": {
        "price": 250000000.0,
        "income": "25000",
        "consumption": "3000"
    },
    "Газпром": {
        "price": 1000000000.0,
        "income": "100000",
        "consumption": "12000"
    }
}